{"address": {"uspsPreferredCityName": "ROSEDALE", "fireCompanyType": "E", "fromLionNodeId": "0039348", "cooperativeIdNumber": "0000", "dotStreetLightContractorArea": "4", "lionBoroughCodeForVanityAddress": "4", "zipCode": "11422", "fireCompanyNumber": "314", "communityDistrict": "413", "firstStreetNameNormalized": "BROOKVILLE BOULEVARD", "boroughCode1In": "4", "latitude": 40.6688956449045, "giSideOfStreetIndicator1": "L", "lowHouseNumberOfBlockfaceSortFormat": "100137025AA", "gi5DigitStreetCode1": "37420", "assemblyDistrict": "29", "yCoordinate": "0183083", "lionBoroughCode": "4", "interimAssistanceEligibilityIndicator": "I", "communityDistrictNumber": "13", "communityDistrictBoroughCode": "4", "condominiumBillingBbl": "0000000000", "instructionalRegion": "QS", "sanitationCollectionSchedulingSectionAndSubsection": "7C", "workAreaFormatIndicatorIn": "C", "fireDivision": "13", "listOf4Lgcs": "01", "sanbornBoroughCode": "4", "boePreferredStreetName": "BROOKVILLE BOULEVARD", "lionSequenceNumber": "00170", "healthArea": "3531", "dynamicBlock": "409", "bblTaxBlock": "13235", "houseNumberSortFormat": "100137035AA", "firstBoroughName": "QUEENS", "numberOfCrossStreetsLowAddressEnd": "1", "taxMapNumberSectionAndVolume": "45505", "electionDistrict": "068", "yCoordinateHighAddressEnd": "0182975", "boardOfElectionsPreferredLgc": "1", "highHouseNumberOfBlockfaceSortFormat": "100137043AA", "message2": "INPUT STREET NAME HAS BEEN MODIFIED", "lowCrossStreetB5SC1": "422440", "roadwayType": "1", "giBoroughCode2": "4", "giBoroughCode1": "4", "firstStreetCode": "43742001010", "healthCenterDistrict": "44", "yCoordinateLowAddressEnd": "0183212", "highCrossStreetB5SC1": "422520", "geosupportReturnCode": "00", "toLionNodeId": "0039346", "sanitationSnowPriorityCode": "P", "numberOfCrossStreetsHighAddressEnd": "1", "giLowHouseNumber1": "137-35", "sideOfStreetOfVanityAddress": "L", "nta": "QN05", "bblTaxLot": "0012", "houseNumber": "137-35", "genericId": "0009775", "numberOfCrossStreetB5SCsHighAddressEnd": "1", "giStreetCode2": "43742001", "giStreetCode1": "43742001", "geosupportReturnCode2": "01", "numberOfEntriesInListOfGeographicIdentifiers": "0002", "hurricaneEvacuationZone": "5", "giHighHouseNumber1": "137-43", "segmentAzimuth": "246", "fireBattalion": "54", "yCoordinateOfCenterofCurvature": "0000000", "numberOfExistingStructuresOnLot": "0002", "lionKeyForVanityAddress": "4145200170", "censusBlock2000": "4011", "physicalId": "0011572", "buildingIdentificationNumber": "4284383", "sanitationRegularCollectionSchedule": "MTH", "lionFaceCode": "1452", "cityCouncilDistrict": "31", "internalLabelXCoordinate": "1057384", "sanitationDistrict": "413", "bbl": "4132350012", "underlyingStreetCode": "43742001", "sanitationRecyclingCollectionSchedule": "EM", "longitudeInternalLabel": -73.7363695781061, "highCrossStreetCode1": "42252001", "coincidentSegmentCount": "1", "returnCode1a": "01", "censusBlock2010": "2002", "lionFaceCodeForVanityAddress": "1452", "returnCode1e": "00", "sanbornPageNumber": "083", "streetStatus": "2", "reasonCode2": "W", "crossStreetNamesFlagIn": "E", "lionKey": "4145200170", "latitudeInternalLabel": 40.66858227107898, "houseNumberIn": "137-35", "dcpPreferredLgc": "01", "segmentOrientation": "3", "fromPreferredLgcsFirstSetOf5": "01", "giBuildingIdentificationNumber1": "4284383", "giBuildingIdentificationNumber2": "4528502", "sideOfStreetIndicator": "L", "toPreferredLgcsFirstSetOf5": "01", "lionSequenceNumberForVanityAddress": "00170", "gi5DigitStreetCode2": "37420", "highBblOfThisBuildingsCondominiumUnits": "4132350012", "numberOfStreetFrontagesOfLot": "01", "trafficDirection": "T", "boePreferredstreetCode": "43742001", "longitude": -73.73657381231172, "stateSenatorialDistrict": "14", "censusTract2010": " 638  ", "segmentLengthInFeet": "00257", "xCoordinateHighAddressEnd": "1057278", "numberOfCrossStreetB5SCsLowAddressEnd": "1", "communitySchoolDistrict": "29", "sanbornVolumeNumber": "14", "policePrecinct": "105", "censusTract1990": " 638  ", "internalLabelYCoordinate": "0182969", "bblBoroughCode": "4", "splitLowHouseNumber": "100137025AA", "rpadBuildingClassificationCode": "M3", "giDcpPreferredLgc1": "01", "giDcpPreferredLgc2": "01", "censusTract2000": " 638  ", "giStreetName1": "BROOKVILLE BOULEVARD", "reasonCode1a": "W", "giStreetName2": "BROOKVILLE BOULEVARD", "segmentTypeCode": "U", "geosupportFunctionCode": "1B", "lowCrossStreetCode1": "42244001", "congressionalDistrict": "05", "xCoordinate": "1057327", "lowCrossStreetName1": "137 ROAD", "policePatrolBoroughCommand": "8", "rpadSelfCheckCodeForBbl": "2", "streetName1In": "BROOKVILLE BLVD ,", "segmentIdentifier": "0063798", "civilCourtDistrict": "04", "lowBblOfThisBuildingsCondominiumUnits": "4132350012", "giGeographicIdentifier2": "B", "highCrossStreetName1": "138 AVENUE", "ntaName": "Rosedale", "lowHouseNumberOfDefiningAddressRange": "100137035AA", "legacySegmentId": "0063798", "xCoordinateOfCenterofCurvature": "0000000", "xCoordinateLowAddressEnd": "1057379"}}