{"address": {"uspsPreferredCityName": "JACKSON HEIGHTS", "fireCompanyType": "E", "fromLionNodeId": "0046630", "dotStreetLightContractorArea": "4", "lionBoroughCodeForVanityAddress": "4", "zipCode": "11372", "fireCompanyNumber": "307", "communityDistrict": "403", "firstStreetNameNormalized": "79 STREET", "boroughCode1In": "4", "latitude": 40.75113099779418, "giSideOfStreetIndicator1": "L", "lowHouseNumberOfBlockfaceSortFormat": "100035001AA", "gi5DigitStreetCode1": "16490", "assemblyDistrict": "39", "yCoordinate": "0212954", "lionBoroughCode": "4", "communityDistrictNumber": "03", "communityDistrictBoroughCode": "4", "condominiumBillingBbl": "0000000000", "instructionalRegion": "QN", "sanitationCollectionSchedulingSectionAndSubsection": "2D", "workAreaFormatIndicatorIn": "C", "fireDivision": "14", "listOf4Lgcs": "01", "sanbornBoroughCode": "4", "boePreferredStreetName": "79 STREET", "lionSequenceNumber": "01090", "healthArea": "1011", "dynamicBlock": "302", "bblTaxBlock": "01279", "houseNumberSortFormat": "100035045AA", "firstBoroughName": "QUEENS", "numberOfCrossStreetsLowAddressEnd": "1", "taxMapNumberSectionAndVolume": "40804", "electionDistrict": "045", "yCoordinateHighAddressEnd": "0212343", "boardOfElectionsPreferredLgc": "1", "highHouseNumberOfBlockfaceSortFormat": "100036099AA", "message2": "INPUT STREET NAME HAS BEEN MODIFIED", "lowCrossStreetB5SC1": "408590", "roadwayType": "1", "giBoroughCode1": "4", "firstStreetCode": "41649001010", "healthCenterDistrict": "42", "yCoordinateLowAddressEnd": "0213086", "highCrossStreetB5SC1": "408790", "geosupportReturnCode": "00", "toLionNodeId": "0046625", "sanitationSnowPriorityCode": "S", "numberOfCrossStreetsHighAddressEnd": "1", "giLowHouseNumber1": "35-43", "sideOfStreetOfVanityAddress": "L", "nta": "QN28", "bblTaxLot": "0046", "longitudeInternalLabel": -73.88695350901583, "genericId": "0028308", "numberOfCrossStreetB5SCsHighAddressEnd": "1", "giStreetCode1": "41649001", "geosupportReturnCode2": "01", "numberOfEntriesInListOfGeographicIdentifiers": "0001", "hurricaneEvacuationZone": "X", "giHighHouseNumber1": "35-45", "segmentAzimuth": "277", "fireBattalion": "49", "yCoordinateOfCenterofCurvature": "0000000", "numberOfExistingStructuresOnLot": "0001", "lionKeyForVanityAddress": "4591201090", "censusBlock2000": "3000", "physicalId": "0032782", "buildingIdentificationNumber": "4029671", "sanitationRegularCollectionSchedule": "TF", "lionFaceCode": "5912", "cityCouncilDistrict": "25", "internalLabelXCoordinate": "1015572", "sanitationDistrict": "403", "bbl": "4012790046", "underlyingStreetCode": "41649001", "sanitationRecyclingCollectionSchedule": "EF", "houseNumber": "35-45", "highCrossStreetCode1": "40879002", "coincidentSegmentCount": "1", "returnCode1a": "01", "censusBlock2010": "3000", "lionFaceCodeForVanityAddress": "5912", "returnCode1e": "00", "sanbornPageNumber": "012", "streetStatus": "2", "reasonCode2": "W", "crossStreetNamesFlagIn": "E", "lionKey": "4591201090", "latitudeInternalLabel": 40.750227545339605, "houseNumberIn": "35-45", "dcpPreferredLgc": "01", "segmentOrientation": "S", "fromPreferredLgcsFirstSetOf5": "01", "giBuildingIdentificationNumber1": "4029671", "sideOfStreetIndicator": "L", "toPreferredLgcsFirstSetOf5": "02", "lionSequenceNumberForVanityAddress": "01090", "highBblOfThisBuildingsCondominiumUnits": "4012790046", "numberOfStreetFrontagesOfLot": "01", "trafficDirection": "A", "boePreferredstreetCode": "41649001", "longitude": -73.88739230109125, "stateSenatorialDistrict": "13", "censusTract2010": " 285  ", "segmentLengthInFeet": "00751", "xCoordinateHighAddressEnd": "1015532", "numberOfCrossStreetB5SCsLowAddressEnd": "1", "communitySchoolDistrict": "30", "sanbornVolumeNumber": "10", "policePrecinct": "115", "censusTract1990": " 285  ", "internalLabelYCoordinate": "0212625", "bblBoroughCode": "4", "splitLowHouseNumber": "100035001AA", "rpadBuildingClassificationCode": "D4", "giDcpPreferredLgc1": "01", "cooperativeIdNumber": "1", "censusTract2000": " 285  ", "giStreetName1": "79 STREET", "reasonCode1a": "W", "interimAssistanceEligibilityIndicator": "I", "segmentTypeCode": "U", "geosupportFunctionCode": "1B", "lowCrossStreetCode1": "40859001", "congressionalDistrict": "14", "xCoordinate": "1015450", "lowCrossStreetName1": "35 AVENUE", "policePatrolBoroughCommand": "6", "rpadSelfCheckCodeForBbl": "2", "streetName1In": "79TH ST,", "segmentIdentifier": "0076224", "civilCourtDistrict": "02", "lowBblOfThisBuildingsCondominiumUnits": "4012790046", "highCrossStreetName1": "37 AVENUE", "ntaName": "Jackson Heights", "lowHouseNumberOfDefiningAddressRange": "100035043AA", "legacySegmentId": "0076224", "xCoordinateOfCenterofCurvature": "0000000", "xCoordinateLowAddressEnd": "1015428"}}