{"address": {"uspsPreferredCityName": "JACKSON HEIGHTS", "fireCompanyType": "E", "fromLionNodeId": "0046479", "dotStreetLightContractorArea": "4", "lionBoroughCodeForVanityAddress": "4", "zipCode": "11372", "fireCompanyNumber": "307", "communityDistrict": "403", "firstStreetNameNormalized": "73 STREET", "boroughCode1In": "4", "latitude": 40.7505324769655, "giSideOfStreetIndicator1": "L", "lowHouseNumberOfBlockfaceSortFormat": "100035001AA", "gi5DigitStreetCode1": "15540", "assemblyDistrict": "34", "yCoordinate": "0212734", "lionBoroughCode": "4", "communityDistrictNumber": "03", "communityDistrictBoroughCode": "4", "condominiumBillingBbl": "0000000000", "instructionalRegion": "QN", "sanitationCollectionSchedulingSectionAndSubsection": "2C", "workAreaFormatIndicatorIn": "C", "fireDivision": "14", "listOf4Lgcs": "01", "sanbornBoroughCode": "4", "boePreferredStreetName": "73 STREET", "lionSequenceNumber": "01070", "healthArea": "1022", "dynamicBlock": "306", "bblTaxBlock": "01273", "houseNumberSortFormat": "100035055AA", "firstBoroughName": "QUEENS", "numberOfCrossStreetsLowAddressEnd": "1", "taxMapNumberSectionAndVolume": "40804", "electionDistrict": "028", "yCoordinateHighAddressEnd": "0212126", "boardOfElectionsPreferredLgc": "1", "highHouseNumberOfBlockfaceSortFormat": "100036099AA", "message2": "INPUT STREET NAME HAS BEEN MODIFIED", "lowCrossStreetB5SC1": "408590", "roadwayType": "1", "giBoroughCode1": "4", "firstStreetCode": "41554001010", "healthCenterDistrict": "42", "yCoordinateLowAddressEnd": "0212871", "highCrossStreetB5SC1": "408790", "geosupportReturnCode": "00", "toLionNodeId": "0046480", "sanitationSnowPriorityCode": "P", "numberOfCrossStreetsHighAddressEnd": "1", "giLowHouseNumber1": "35-55", "sideOfStreetOfVanityAddress": "L", "nta": "QN28", "bblTaxLot": "0044", "longitudeInternalLabel": -73.8925414182892, "genericId": "0028209", "numberOfCrossStreetB5SCsHighAddressEnd": "1", "giStreetCode1": "41554001", "geosupportReturnCode2": "01", "numberOfEntriesInListOfGeographicIdentifiers": "0001", "hurricaneEvacuationZone": "X", "giHighHouseNumber1": "35-55", "segmentAzimuth": "277", "fireBattalion": "49", "yCoordinateOfCenterofCurvature": "0000000", "numberOfExistingStructuresOnLot": "0001", "lionKeyForVanityAddress": "4584801070", "censusBlock2000": "3001", "physicalId": "0032678", "buildingIdentificationNumber": "4029560", "sanitationRegularCollectionSchedule": "MTH", "lionFaceCode": "5848", "cityCouncilDistrict": "25", "internalLabelXCoordinate": "1014024", "sanitationDistrict": "403", "bbl": "4012730044", "underlyingStreetCode": "41554001", "sanitationRecyclingCollectionSchedule": "ETH", "houseNumber": "35-55", "highCrossStreetCode1": "40879002", "coincidentSegmentCount": "1", "returnCode1a": "01", "censusBlock2010": "3001", "lionFaceCodeForVanityAddress": "5848", "returnCode1e": "00", "sanbornPageNumber": "010", "streetStatus": "2", "reasonCode2": "W", "crossStreetNamesFlagIn": "E", "lionKey": "4584801070", "latitudeInternalLabel": 40.74966473077041, "houseNumberIn": "35-55", "dcpPreferredLgc": "01", "segmentOrientation": "S", "fromPreferredLgcsFirstSetOf5": "01", "giBuildingIdentificationNumber1": "4029560", "sideOfStreetIndicator": "L", "toPreferredLgcsFirstSetOf5": "02", "lionSequenceNumberForVanityAddress": "01070", "highBblOfThisBuildingsCondominiumUnits": "4012730044", "numberOfStreetFrontagesOfLot": "01", "trafficDirection": "W", "boePreferredstreetCode": "41554001", "longitude": -73.8929767305771, "stateSenatorialDistrict": "13", "censusTract2010": " 289  ", "segmentLengthInFeet": "00751", "xCoordinateHighAddressEnd": "1013978", "numberOfCrossStreetB5SCsLowAddressEnd": "1", "communitySchoolDistrict": "30", "sanbornVolumeNumber": "10", "policePrecinct": "115", "censusTract1990": " 289  ", "internalLabelYCoordinate": "0212418", "bblBoroughCode": "4", "splitLowHouseNumber": "100035001AA", "rpadBuildingClassificationCode": "D1", "giDcpPreferredLgc1": "01", "cooperativeIdNumber": "0000", "censusTract2000": " 289  ", "giStreetName1": "73 STREET", "reasonCode1a": "W", "interimAssistanceEligibilityIndicator": "E", "segmentTypeCode": "U", "geosupportFunctionCode": "1B", "lowCrossStreetCode1": "40859001", "congressionalDistrict": "14", "xCoordinate": "1013903", "lowCrossStreetName1": "35 AVENUE", "policePatrolBoroughCommand": "6", "rpadSelfCheckCodeForBbl": "0", "streetName1In": "73RD ST,", "segmentIdentifier": "0075945", "civilCourtDistrict": "02", "lowBblOfThisBuildingsCondominiumUnits": "4012730044", "highCrossStreetName1": "37 AVENUE", "ntaName": "Jackson Heights", "lowHouseNumberOfDefiningAddressRange": "100035055AA", "legacySegmentId": "0075945", "xCoordinateOfCenterofCurvature": "0000000", "xCoordinateLowAddressEnd": "1013883"}}